{
  "dashboards": [
{"name": "admin admin", "created": "2023-08-06T20:34:15.952", "lastUpdated": "2025-06-16T06:36:12.429", "translations": [], "id": "M5zQapPyTZI", "code": "admin", "displayName": "admin admin", "username": "admin"},
{"id": "rNy9m4YxyPh", "created": "2026-02-18T15:44:06.456973", "lastUpdated": "2026-02-18T15:44:06.456981", "name": "Bladder Cancer Dashboard", "displayName": "Bladder Cancer Dashboard", "description": "Monitoring dashboard for Bladder cancer program - includes case tracking, treatment outcomes, and program indicators", "dashboardItems": [{"id": "95af9b26-e0", "type": "VISUALIZATION"}, {"id": "42ac030c-d5", "type": "VISUALIZATION"}, {"id": "c60597a0-c5", "type": "VISUALIZATION"}, {"id": "b837cc47-8b", "type": "VISUALIZATION"}], "dashboardType": "PROGRAM", "favorite": false, "owner": "dhis2user", "external": false},
{"id": "c3km9x4SvBc", "created": "2026-02-18T15:44:06.457044", "lastUpdated": "2026-02-18T15:44:06.457046", "name": "Breast Cancer Dashboard", "displayName": "Breast Cancer Dashboard", "description": "Monitoring dashboard for Breast cancer program - includes case tracking, treatment outcomes, and program indicators", "dashboardItems": [{"id": "d11dabc4-ef", "type": "VISUALIZATION"}, {"id": "0e3d5cac-76", "type": "VISUALIZATION"}, {"id": "9be17718-c3", "type": "VISUALIZATION"}, {"id": "64bfe308-83", "type": "VISUALIZATION"}], "dashboardType": "PROGRAM", "favorite": false, "owner": "dhis2user", "external": false},
{"id": "gcwO8zw4iDx", "created": "2026-02-18T15:44:06.457081", "lastUpdated": "2026-02-18T15:44:06.457083", "name": "Colorectal Cancer Dashboard", "displayName": "Colorectal Cancer Dashboard", "description": "Monitoring dashboard for Colorectal cancer program - includes case tracking, treatment outcomes, and program indicators", "dashboardItems": [{"id": "4dda4e4f-d2", "type": "VISUALIZATION"}, {"id": "e5b03e6f-24", "type": "VISUALIZATION"}, {"id": "64a9e569-39", "type": "VISUALIZATION"}, {"id": "e3eba9c3-ff", "type": "VISUALIZATION"}], "dashboardType": "PROGRAM", "favorite": false, "owner": "dhis2user", "external": false},
{"id": "CQKmlhHajww", "created": "2026-02-18T15:44:06.457122", "lastUpdated": "2026-02-18T15:44:06.457124", "name": "Esophageal Cancer Dashboard", "displayName": "Esophageal Cancer Dashboard", "description": "Monitoring dashboard for Esophageal cancer program - includes case tracking, treatment outcomes, and program indicators", "dashboardItems": [{"id": "62e13358-78", "type": "VISUALIZATION"}, {"id": "fe69179b-56", "type": "VISUALIZATION"}, {"id": "0448997c-b8", "type": "VISUALIZATION"}, {"id": "054d4de0-94", "type": "VISUALIZATION"}], "dashboardType": "PROGRAM", "favorite": false, "owner": "dhis2user", "external": false},
{"id": "Npy7Rh9GEsL", "created": "2026-02-18T15:44:06.457158", "lastUpdated": "2026-02-18T15:44:06.457159", "name": "Kaposi Sarcoma Cancer Dashboard", "displayName": "Kaposi Sarcoma Cancer Dashboard", "description": "Monitoring dashboard for Kaposi Sarcoma cancer program - includes case tracking, treatment outcomes, and program indicators", "dashboardItems": [{"id": "b922743c-ca", "type": "VISUALIZATION"}, {"id": "c3a05aec-bf", "type": "VISUALIZATION"}, {"id": "3bf781fd-dd", "type": "VISUALIZATION"}, {"id": "06d9fd1c-31", "type": "VISUALIZATION"}], "dashboardType": "PROGRAM", "favorite": false, "owner": "dhis2user", "external": false},
{"id": "XQh7pd2HRhO", "created": "2026-02-18T15:44:06.457191", "lastUpdated": "2026-02-18T15:44:06.457192", "name": "Kidney Cancer Dashboard", "displayName": "Kidney Cancer Dashboard", "description": "Monitoring dashboard for Kidney cancer program - includes case tracking, treatment outcomes, and program indicators", "dashboardItems": [{"id": "ac134ff2-b5", "type": "VISUALIZATION"}, {"id": "68d51212-7f", "type": "VISUALIZATION"}, {"id": "638e7218-a9", "type": "VISUALIZATION"}, {"id": "7f461f53-b5", "type": "VISUALIZATION"}], "dashboardType": "PROGRAM", "favorite": false, "owner": "dhis2user", "external": false},
{"id": "niUxxMkNEVE", "created": "2026-02-18T15:44:06.457224", "lastUpdated": "2026-02-18T15:44:06.457225", "name": "Leukemia Cancer Dashboard", "displayName": "Leukemia Cancer Dashboard", "description": "Monitoring dashboard for Leukemia cancer program - includes case tracking, treatment outcomes, and program indicators", "dashboardItems": [{"id": "5d8eba26-1c", "type": "VISUALIZATION"}, {"id": "64d60a15-59", "type": "VISUALIZATION"}, {"id": "e304bf4e-0b", "type": "VISUALIZATION"}, {"id": "603a5852-67", "type": "VISUALIZATION"}], "dashboardType": "PROGRAM", "favorite": false, "owner": "dhis2user", "external": false},
{"id": "uCtEEA9zn7T", "created": "2026-02-18T15:44:06.457257", "lastUpdated": "2026-02-18T15:44:06.457258", "name": "Liver Cancer Dashboard", "displayName": "Liver Cancer Dashboard", "description": "Monitoring dashboard for Liver cancer program - includes case tracking, treatment outcomes, and program indicators", "dashboardItems": [{"id": "6015d8dd-94", "type": "VISUALIZATION"}, {"id": "74598130-58", "type": "VISUALIZATION"}, {"id": "a73c6980-a6", "type": "VISUALIZATION"}, {"id": "c77ea032-38", "type": "VISUALIZATION"}], "dashboardType": "PROGRAM", "favorite": false, "owner": "dhis2user", "external": false},
{"id": "RhlD6znA3FX", "created": "2026-02-18T15:44:06.457293", "lastUpdated": "2026-02-18T15:44:06.457294", "name": "Lung Cancer Dashboard", "displayName": "Lung Cancer Dashboard", "description": "Monitoring dashboard for Lung cancer program - includes case tracking, treatment outcomes, and program indicators", "dashboardItems": [{"id": "e5225c71-17", "type": "VISUALIZATION"}, {"id": "beabed25-b8", "type": "VISUALIZATION"}, {"id": "1103b106-c9", "type": "VISUALIZATION"}, {"id": "0c169c9a-12", "type": "VISUALIZATION"}], "dashboardType": "PROGRAM", "favorite": false, "owner": "dhis2user", "external": false},
{"id": "dJPlC7cLKXh", "created": "2026-02-18T15:44:06.457326", "lastUpdated": "2026-02-18T15:44:06.457328", "name": "Lymphoma Cancer Dashboard", "displayName": "Lymphoma Cancer Dashboard", "description": "Monitoring dashboard for Lymphoma cancer program - includes case tracking, treatment outcomes, and program indicators", "dashboardItems": [{"id": "c6e68ad2-80", "type": "VISUALIZATION"}, {"id": "73b0ede0-e5", "type": "VISUALIZATION"}, {"id": "625fd2a1-f7", "type": "VISUALIZATION"}, {"id": "80485467-86", "type": "VISUALIZATION"}], "dashboardType": "PROGRAM", "favorite": false, "owner": "dhis2user", "external": false},
{"id": "pKZgtaZpa7i", "created": "2026-02-18T15:44:06.457360", "lastUpdated": "2026-02-18T15:44:06.457361", "name": "Oral Head Neck Cancer Dashboard", "displayName": "Oral Head Neck Cancer Dashboard", "description": "Monitoring dashboard for Oral Head Neck cancer program - includes case tracking, treatment outcomes, and program indicators", "dashboardItems": [{"id": "af2af017-e4", "type": "VISUALIZATION"}, {"id": "a9445b8a-fa", "type": "VISUALIZATION"}, {"id": "af44d8dc-c7", "type": "VISUALIZATION"}, {"id": "b02254e8-9f", "type": "VISUALIZATION"}], "dashboardType": "PROGRAM", "favorite": false, "owner": "dhis2user", "external": false},
{"id": "W9JXG5bBbpg", "created": "2026-02-18T15:44:06.457393", "lastUpdated": "2026-02-18T15:44:06.457394", "name": "Ovarian Cancer Dashboard", "displayName": "Ovarian Cancer Dashboard", "description": "Monitoring dashboard for Ovarian cancer program - includes case tracking, treatment outcomes, and program indicators", "dashboardItems": [{"id": "4995c31b-e8", "type": "VISUALIZATION"}, {"id": "c31d7c21-fc", "type": "VISUALIZATION"}, {"id": "f9e38bcc-92", "type": "VISUALIZATION"}, {"id": "dcecbc36-09", "type": "VISUALIZATION"}], "dashboardType": "PROGRAM", "favorite": false, "owner": "dhis2user", "external": false},
{"id": "apF4DSQz350", "created": "2026-02-18T15:44:06.457426", "lastUpdated": "2026-02-18T15:44:06.457427", "name": "Pancreatic Cancer Dashboard", "displayName": "Pancreatic Cancer Dashboard", "description": "Monitoring dashboard for Pancreatic cancer program - includes case tracking, treatment outcomes, and program indicators", "dashboardItems": [{"id": "887c1c31-85", "type": "VISUALIZATION"}, {"id": "03415877-4b", "type": "VISUALIZATION"}, {"id": "3f1526de-14", "type": "VISUALIZATION"}, {"id": "3888f8a5-22", "type": "VISUALIZATION"}], "dashboardType": "PROGRAM", "favorite": false, "owner": "dhis2user", "external": false},
{"id": "G5fXvvwQe9n", "created": "2026-02-18T15:44:06.457459", "lastUpdated": "2026-02-18T15:44:06.457460", "name": "Prostate Cancer Dashboard", "displayName": "Prostate Cancer Dashboard", "description": "Monitoring dashboard for Prostate cancer program - includes case tracking, treatment outcomes, and program indicators", "dashboardItems": [{"id": "eca17f1c-fe", "type": "VISUALIZATION"}, {"id": "c4386b2d-dd", "type": "VISUALIZATION"}, {"id": "90d7c0fc-cc", "type": "VISUALIZATION"}, {"id": "3d7cb02b-93", "type": "VISUALIZATION"}], "dashboardType": "PROGRAM", "favorite": false, "owner": "dhis2user", "external": false},
{"id": "IT5f54zF0zx", "created": "2026-02-18T15:44:06.457492", "lastUpdated": "2026-02-18T15:44:06.457493", "name": "Skin Melanoma Cancer Dashboard", "displayName": "Skin Melanoma Cancer Dashboard", "description": "Monitoring dashboard for Skin Melanoma cancer program - includes case tracking, treatment outcomes, and program indicators", "dashboardItems": [{"id": "78324755-61", "type": "VISUALIZATION"}, {"id": "58815c09-c4", "type": "VISUALIZATION"}, {"id": "62b60dc7-80", "type": "VISUALIZATION"}, {"id": "e84160fb-a0", "type": "VISUALIZATION"}], "dashboardType": "PROGRAM", "favorite": false, "owner": "dhis2user", "external": false},
{"id": "TXxS0QIqePT", "created": "2026-02-18T15:44:06.457525", "lastUpdated": "2026-02-18T15:44:06.457526", "name": "Stomach Cancer Dashboard", "displayName": "Stomach Cancer Dashboard", "description": "Monitoring dashboard for Stomach cancer program - includes case tracking, treatment outcomes, and program indicators", "dashboardItems": [{"id": "ba13b721-6e", "type": "VISUALIZATION"}, {"id": "b52fb333-12", "type": "VISUALIZATION"}, {"id": "e0c0a87b-90", "type": "VISUALIZATION"}, {"id": "02f5f8f4-10", "type": "VISUALIZATION"}], "dashboardType": "PROGRAM", "favorite": false, "owner": "dhis2user", "external": false},
{"id": "vBPD6GM3LgJ", "created": "2026-02-18T15:44:06.457558", "lastUpdated": "2026-02-18T15:44:06.457560", "name": "Testicular Cancer Dashboard", "displayName": "Testicular Cancer Dashboard", "description": "Monitoring dashboard for Testicular cancer program - includes case tracking, treatment outcomes, and program indicators", "dashboardItems": [{"id": "3c38d77f-a8", "type": "VISUALIZATION"}, {"id": "6c55d313-85", "type": "VISUALIZATION"}, {"id": "67386597-db", "type": "VISUALIZATION"}, {"id": "ce04cf40-7a", "type": "VISUALIZATION"}], "dashboardType": "PROGRAM", "favorite": false, "owner": "dhis2user", "external": false},
{"id": "qMLfDzfOcnq", "created": "2026-02-18T15:44:06.457592", "lastUpdated": "2026-02-18T15:44:06.457593", "name": "Thyroid Cancer Dashboard", "displayName": "Thyroid Cancer Dashboard", "description": "Monitoring dashboard for Thyroid cancer program - includes case tracking, treatment outcomes, and program indicators", "dashboardItems": [{"id": "b7e65883-13", "type": "VISUALIZATION"}, {"id": "f1d89867-42", "type": "VISUALIZATION"}, {"id": "eb27a247-2b", "type": "VISUALIZATION"}, {"id": "c6f0ed86-e9", "type": "VISUALIZATION"}], "dashboardType": "PROGRAM", "favorite": false, "owner": "dhis2user", "external": false}
  ]
}
