{"system":{"id":"039b6994-a3e7-4531-967d-d5db7fceb5eb","rev":"dfd7f48","version":"2.40.5","date":"2026-02-17T18:13:36.427+0000"},"categoryOptionCombos":[{"name":"HIV unknown, 15-19","created":"2023-08-02T06:55:57.928","lastUpdated":"2023-08-02T06:55:57.928","translations":[],"lastUpdatedBy":{"id":"M5zQapPyTZI","code":"admin","name":"admin admin","displayName":"admin admin","username":"admin"},"categoryCombo":{"id":"xDsPPFKU2mh"},"categoryOptions":[{"id":"Vuc1BJSOorP"},{"id":"AdOGHNfJJgn"}],"ignoreApproval":false,"id":"bLDRneBNgHU","attributeValues":[]},{"name":"HIV unknown, 20-24","created":"2023-08-02T06:55:57.936","lastUpdated":"2023-08-02T06:55:57.936","translations":[],"lastUpdatedBy":{"id":"M5zQapPyTZI","code":"admin","name":"admin admin","displayName":"admin admin","username":"admin"},"categoryCombo":{"id":"xDsPPFKU2mh"},"categoryOptions":[{"id":"AdOGHNfJJgn"},{"id":"bhx5ONCot8V"}],"ignoreApproval":false,"id":"AvGbVPES0dC","attributeValues":[]},{"name":"HIV unknown, 25-29","created":"2023-08-02T06:55:57.940","lastUpdated":"2023-08-02T06:55:57.940","translations":[],"lastUpdatedBy":{"id":"M5zQapPyTZI","code":"admin","name":"admin admin","displayName":"admin admin","username":"admin"},"categoryCombo":{"id":"xDsPPFKU2mh"},"categoryOptions":[{"id":"TM5zVeshQyh"},{"id":"AdOGHNfJJgn"}],"ignoreApproval":false,"id":"rHCYm1fzR7c","attributeValues":[]},{"name":"HIV unknown, 30-34","created":"2023-08-02T06:55:57.942","lastUpdated":"2023-08-02T06:55:57.942","translations":[],"lastUpdatedBy":{"id":"M5zQapPyTZI","code":"admin","name":"admin admin","displayName":"admin admin","username":"admin"},"categoryCombo":{"id":"xDsPPFKU2mh"},"categoryOptions":[{"id":"AdOGHNfJJgn"},{"id":"kKiTqS6Vd0X"}],"ignoreApproval":false,"id":"JpCU73H2pkx","attributeValues":[]},{"name":"HIV unknown, 35-39","created":"2023-08-02T06:55:57.945","lastUpdated":"2023-08-02T06:55:57.945","translations":[],"lastUpdatedBy":{"id":"M5zQapPyTZI","code":"admin","name":"admin admin","displayName":"admin admin","username":"admin"},"categoryCombo":{"id":"xDsPPFKU2mh"},"categoryOptions":[{"id":"AdOGHNfJJgn"},{"id":"nqR6XXBM6cn"}],"ignoreApproval":false,"id":"JfgX45Vj3d7","attributeValues":[]},{"name":"HIV unknown, 40-44","created":"2023-08-02T06:55:57.947","lastUpdated":"2023-08-02T06:55:57.947","translations":[],"lastUpdatedBy":{"id":"M5zQapPyTZI","code":"admin","name":"admin admin","displayName":"admin admin","username":"admin"},"categoryCombo":{"id":"xDsPPFKU2mh"},"categoryOptions":[{"id":"AdOGHNfJJgn"},{"id":"dib8KvXIgHA"}],"ignoreApproval":false,"id":"V0oBp7MlO1n","attributeValues":[]},{"name":"HIV unknown, 45-49","created":"2023-08-02T06:55:57.950","lastUpdated":"2023-08-02T06:55:57.950","translations":[],"lastUpdatedBy":{"id":"M5zQapPyTZI","code":"admin","name":"admin admin","displayName":"admin admin","username":"admin"},"categoryCombo":{"id":"xDsPPFKU2mh"},"categoryOptions":[{"id":"DkgPXtR2ZXX"},{"id":"AdOGHNfJJgn"}],"ignoreApproval":false,"id":"Mr0AEgFlh0m","attributeValues":[]},{"name":"HIV unknown, 50+","created":"2023-08-02T06:55:57.952","lastUpdated":"2023-08-02T06:55:57.952","translations":[],"lastUpdatedBy":{"id":"M5zQapPyTZI","code":"admin","name":"admin admin","displayName":"admin admin","username":"admin"},"categoryCombo":{"id":"xDsPPFKU2mh"},"categoryOptions":[{"id":"lvri1b2Mq4v"},{"id":"AdOGHNfJJgn"}],"ignoreApproval":false,"id":"quVcAkRAhJi","attributeValues":[]},{"name":"HIV unknown, Age unknown","created":"2023-08-12T03:42:58.552","lastUpdated":"2023-08-12T03:42:58.552","translations":[],"lastUpdatedBy":{"id":"M5zQapPyTZI","code":"admin","name":"admin admin","displayName":"admin admin","username":"admin"},"categoryCombo":{"id":"xDsPPFKU2mh"},"categoryOptions":[{"id":"OGXWo79Rw0G"},{"id":"AdOGHNfJJgn"}],"ignoreApproval":false,"id":"LqHIASvHHAM","attributeValues":[]},{"name":"HIV+, 15-19","created":"2023-08-02T06:55:57.924","lastUpdated":"2023-08-02T06:55:57.924","translations":[],"lastUpdatedBy":{"id":"M5zQapPyTZI","code":"admin","name":"admin admin","displayName":"admin admin","username":"admin"},"categoryCombo":{"id":"xDsPPFKU2mh"},"categoryOptions":[{"id":"Vuc1BJSOorP"},{"id":"JBgOaIyUEJQ"}],"ignoreApproval":false,"id":"odiQoFxwXwg","attributeValues":[]},{"name":"HIV+, 20-24","created":"2023-08-02T06:55:57.933","lastUpdated":"2023-08-02T06:55:57.933","translations":[],"lastUpdatedBy":{"id":"M5zQapPyTZI","code":"admin","name":"admin admin","displayName":"admin admin","username":"admin"},"categoryCombo":{"id":"xDsPPFKU2mh"},"categoryOptions":[{"id":"JBgOaIyUEJQ"},{"id":"bhx5ONCot8V"}],"ignoreApproval":false,"id":"iXYIOrKWiKa","attributeValues":[]},{"name":"HIV+, 25-29","created":"2023-08-02T06:55:57.937","lastUpdated":"2023-08-02T06:55:57.937","translations":[],"lastUpdatedBy":{"id":"M5zQapPyTZI","code":"admin","name":"admin admin","displayName":"admin admin","username":"admin"},"categoryCombo":{"id":"xDsPPFKU2mh"},"categoryOptions":[{"id":"TM5zVeshQyh"},{"id":"JBgOaIyUEJQ"}],"ignoreApproval":false,"id":"UyvpzqGd8EG","attributeValues":[]},{"name":"HIV+, 30-34","created":"2023-08-02T06:55:57.941","lastUpdated":"2023-08-02T06:55:57.941","translations":[],"lastUpdatedBy":{"id":"M5zQapPyTZI","code":"admin","name":"admin admin","displayName":"admin admin","username":"admin"},"categoryCombo":{"id":"xDsPPFKU2mh"},"categoryOptions":[{"id":"JBgOaIyUEJQ"},{"id":"kKiTqS6Vd0X"}],"ignoreApproval":false,"id":"qfv6zCnFjtQ","attributeValues":[]},{"name":"HIV+, 35-39","created":"2023-08-02T06:55:57.943","lastUpdated":"2023-08-02T06:55:57.943","translations":[],"lastUpdatedBy":{"id":"M5zQapPyTZI","code":"admin","name":"admin admin","displayName":"admin admin","username":"admin"},"categoryCombo":{"id":"xDsPPFKU2mh"},"categoryOptions":[{"id":"JBgOaIyUEJQ"},{"id":"nqR6XXBM6cn"}],"ignoreApproval":false,"id":"LEBI3CfNLup","attributeValues":[]},{"name":"HIV+, 40-44","created":"2023-08-02T06:55:57.946","lastUpdated":"2023-08-02T06:55:57.946","translations":[],"lastUpdatedBy":{"id":"M5zQapPyTZI","code":"admin","name":"admin admin","displayName":"admin admin","username":"admin"},"categoryCombo":{"id":"xDsPPFKU2mh"},"categoryOptions":[{"id":"JBgOaIyUEJQ"},{"id":"dib8KvXIgHA"}],"ignoreApproval":false,"id":"SSrWQ5p7rYW","attributeValues":[]},{"name":"HIV+, 45-49","created":"2023-08-02T06:55:57.948","lastUpdated":"2023-08-02T06:55:57.948","translations":[],"lastUpdatedBy":{"id":"M5zQapPyTZI","code":"admin","name":"admin admin","displayName":"admin admin","username":"admin"},"categoryCombo":{"id":"xDsPPFKU2mh"},"categoryOptions":[{"id":"DkgPXtR2ZXX"},{"id":"JBgOaIyUEJQ"}],"ignoreApproval":false,"id":"e6cey8EtG0U","attributeValues":[]},{"name":"HIV+, 50+","created":"2023-08-02T06:55:57.951","lastUpdated":"2023-08-02T06:55:57.951","translations":[],"lastUpdatedBy":{"id":"M5zQapPyTZI","code":"admin","name":"admin admin","displayName":"admin admin","username":"admin"},"categoryCombo":{"id":"xDsPPFKU2mh"},"categoryOptions":[{"id":"lvri1b2Mq4v"},{"id":"JBgOaIyUEJQ"}],"ignoreApproval":false,"id":"Se6o3tnI9xm","attributeValues":[]},{"name":"HIV+, Age unknown","created":"2023-08-12T03:42:58.551","lastUpdated":"2023-08-12T03:42:58.551","translations":[],"lastUpdatedBy":{"id":"M5zQapPyTZI","code":"admin","name":"admin admin","displayName":"admin admin","username":"admin"},"categoryCombo":{"id":"xDsPPFKU2mh"},"categoryOptions":[{"id":"OGXWo79Rw0G"},{"id":"JBgOaIyUEJQ"}],"ignoreApproval":false,"id":"Nnqzq5zJUei","attributeValues":[]},{"name":"HIV-, 15-19","created":"2023-08-02T06:55:57.926","lastUpdated":"2023-08-02T06:55:57.926","translations":[],"lastUpdatedBy":{"id":"M5zQapPyTZI","code":"admin","name":"admin admin","displayName":"admin admin","username":"admin"},"categoryCombo":{"id":"xDsPPFKU2mh"},"categoryOptions":[{"id":"Vuc1BJSOorP"},{"id":"HhshCacVCbE"}],"ignoreApproval":false,"id":"ukfdhEMUGvD","attributeValues":[]},{"name":"HIV-, 20-24","created":"2023-08-02T06:55:57.934","lastUpdated":"2023-08-02T06:55:57.934","translations":[],"lastUpdatedBy":{"id":"M5zQapPyTZI","code":"admin","name":"admin admin","displayName":"admin admin","username":"admin"},"categoryCombo":{"id":"xDsPPFKU2mh"},"categoryOptions":[{"id":"HhshCacVCbE"},{"id":"bhx5ONCot8V"}],"ignoreApproval":false,"id":"MnhEjnmMWLI","attributeValues":[]},{"name":"HIV-, 25-29","created":"2023-08-02T06:55:57.938","lastUpdated":"2023-08-02T06:55:57.938","translations":[],"lastUpdatedBy":{"id":"M5zQapPyTZI","code":"admin","name":"admin admin","displayName":"admin admin","username":"admin"},"categoryCombo":{"id":"xDsPPFKU2mh"},"categoryOptions":[{"id":"TM5zVeshQyh"},{"id":"HhshCacVCbE"}],"ignoreApproval":false,"id":"lHTAEodC1l4","attributeValues":[]},{"name":"HIV-, 30-34","created":"2023-08-02T06:55:57.941","lastUpdated":"2023-08-02T06:55:57.941","translations":[],"lastUpdatedBy":{"id":"M5zQapPyTZI","code":"admin","name":"admin admin","displayName":"admin admin","username":"admin"},"categoryCombo":{"id":"xDsPPFKU2mh"},"categoryOptions":[{"id":"HhshCacVCbE"},{"id":"kKiTqS6Vd0X"}],"ignoreApproval":false,"id":"KkxwBbCRQHu","attributeValues":[]},{"name":"HIV-, 35-39","created":"2023-08-02T06:55:57.944","lastUpdated":"2023-08-02T06:55:57.944","translations":[],"lastUpdatedBy":{"id":"M5zQapPyTZI","code":"admin","name":"admin admin","displayName":"admin admin","username":"admin"},"categoryCombo":{"id":"xDsPPFKU2mh"},"categoryOptions":[{"id":"HhshCacVCbE"},{"id":"nqR6XXBM6cn"}],"ignoreApproval":false,"id":"GD1UxYYprYr","attributeValues":[]},{"name":"HIV-, 40-44","created":"2023-08-02T06:55:57.947","lastUpdated":"2023-08-02T06:55:57.947","translations":[],"lastUpdatedBy":{"id":"M5zQapPyTZI","code":"admin","name":"admin admin","displayName":"admin admin","username":"admin"},"categoryCombo":{"id":"xDsPPFKU2mh"},"categoryOptions":[{"id":"HhshCacVCbE"},{"id":"dib8KvXIgHA"}],"ignoreApproval":false,"id":"kGDThinEbzW","attributeValues":[]},{"name":"HIV-, 45-49","created":"2023-08-02T06:55:57.949","lastUpdated":"2023-08-02T06:55:57.949","translations":[],"lastUpdatedBy":{"id":"M5zQapPyTZI","code":"admin","name":"admin admin","displayName":"admin admin","username":"admin"},"categoryCombo":{"id":"xDsPPFKU2mh"},"categoryOptions":[{"id":"HhshCacVCbE"},{"id":"DkgPXtR2ZXX"}],"ignoreApproval":false,"id":"m9o8lMMnkRr","attributeValues":[]},{"name":"HIV-, 50+","created":"2023-08-02T06:55:57.952","lastUpdated":"2023-08-02T06:55:57.952","translations":[],"lastUpdatedBy":{"id":"M5zQapPyTZI","code":"admin","name":"admin admin","displayName":"admin admin","username":"admin"},"categoryCombo":{"id":"xDsPPFKU2mh"},"categoryOptions":[{"id":"HhshCacVCbE"},{"id":"lvri1b2Mq4v"}],"ignoreApproval":false,"id":"BpUYOW5aMjj","attributeValues":[]},{"name":"HIV-, Age unknown","created":"2023-08-12T03:42:58.552","lastUpdated":"2023-08-12T03:42:58.552","translations":[],"lastUpdatedBy":{"id":"M5zQapPyTZI","code":"admin","name":"admin admin","displayName":"admin admin","username":"admin"},"categoryCombo":{"id":"xDsPPFKU2mh"},"categoryOptions":[{"id":"HhshCacVCbE"},{"id":"OGXWo79Rw0G"}],"ignoreApproval":false,"id":"QYwwrwrHl4p","attributeValues":[]},{"name":"Negative, HIV unknown, 15-19","created":"2023-08-06T05:32:33.248","lastUpdated":"2023-08-06T05:32:33.248","translations":[],"lastUpdatedBy":{"id":"M5zQapPyTZI","code":"admin","name":"admin admin","displayName":"admin admin","username":"admin"},"categoryCombo":{"id":"epRjlDZBrJL"},"categoryOptions":[{"id":"Vuc1BJSOorP"},{"id":"bpham0JX5kw"},{"id":"AdOGHNfJJgn"}],"ignoreApproval":false,"id":"sckRTgseRjD","attributeValues":[]},{"name":"Negative, HIV unknown, 20-24","created":"2023-08-06T05:32:33.248","lastUpdated":"2023-08-06T05:32:33.248","translations":[],"lastUpdatedBy":{"id":"M5zQapPyTZI","code":"admin","name":"admin admin","displayName":"admin admin","username":"admin"},"categoryCombo":{"id":"epRjlDZBrJL"},"categoryOptions":[{"id":"bhx5ONCot8V"},{"id":"bpham0JX5kw"},{"id":"AdOGHNfJJgn"}],"ignoreApproval":false,"id":"Gqpm4tLc7kF","attributeValues":[]},{"name":"Negative, HIV unknown, 25-29","created":"2023-08-06T05:32:33.249","lastUpdated":"2023-08-06T05:32:33.249","translations":[],"lastUpdatedBy":{"id":"M5zQapPyTZI","code":"admin","name":"admin admin","displayName":"admin admin","username":"admin"},"categoryCombo":{"id":"epRjlDZBrJL"},"categoryOptions":[{"id":"TM5zVeshQyh"},{"id":"bpham0JX5kw"},{"id":"AdOGHNfJJgn"}],"ignoreApproval":false,"id":"eMKHBjZGbQb","attributeValues":[]},{"name":"Negative, HIV unknown, 30-34","created":"2023-08-06T05:32:33.250","lastUpdated":"2023-08-06T05:32:33.250","translations":[],"lastUpdatedBy":{"id":"M5zQapPyTZI","code":"admin","name":"admin admin","displayName":"admin admin","username":"admin"},"categoryCombo":{"id":"epRjlDZBrJL"},"categoryOptions":[{"id":"kKiTqS6Vd0X"},{"id":"bpham0JX5kw"},{"id":"AdOGHNfJJgn"}],"ignoreApproval":false,"id":"dNmqdsNA0Bz","attributeValues":[]},{"name":"Negative, HIV unknown, 35-39","created":"2023-08-06T05:32:33.250","lastUpdated":"2023-08-06T05:32:33.250","translations":[],"lastUpdatedBy":{"id":"M5zQapPyTZI","code":"admin","name":"admin admin","displayName":"admin admin","username":"admin"},"categoryCombo":{"id":"epRjlDZBrJL"},"categoryOptions":[{"id":"bpham0JX5kw"},{"id":"AdOGHNfJJgn"},{"id":"nqR6XXBM6cn"}],"ignoreApproval":false,"id":"n3FJDHbdDJq","attributeValues":[]},{"name":"Negative, HIV unknown, 40-44","created":"2023-08-06T05:32:33.251","lastUpdated":"2023-08-06T05:32:33.251","translations":[],"lastUpdatedBy":{"id":"M5zQapPyTZI","code":"admin","name":"admin admin","displayName":"admin admin","username":"admin"},"categoryCombo":{"id":"epRjlDZBrJL"},"categoryOptions":[{"id":"dib8KvXIgHA"},{"id":"bpham0JX5kw"},{"id":"AdOGHNfJJgn"}],"ignoreApproval":false,"id":"hDsQ5iIbXJO","attributeValues":[]},{"name":"Negative, HIV unknown, 45-49","created":"2023-08-06T05:32:33.251","lastUpdated":"2023-08-06T05:32:33.251","translations":[],"lastUpdatedBy":{"id":"M5zQapPyTZI","code":"admin","name":"admin admin","displayName":"admin admin","username":"admin"},"categoryCombo":{"id":"epRjlDZBrJL"},"categoryOptions":[{"id":"DkgPXtR2ZXX"},{"id":"bpham0JX5kw"},{"id":"AdOGHNfJJgn"}],"ignoreApproval":false,"id":"c6R8VM6oh6x","attributeValues":[]},{"name":"Negative, HIV unknown, 50+","created":"2023-08-06T05:32:33.252","lastUpdated":"2023-08-06T05:32:33.252","translations":[],"lastUpdatedBy":{"id":"M5zQapPyTZI","code":"admin","name":"admin admin","displayName":"admin admin","username":"admin"},"categoryCombo":{"id":"epRjlDZBrJL"},"categoryOptions":[{"id":"lvri1b2Mq4v"},{"id":"bpham0JX5kw"},{"id":"AdOGHNfJJgn"}],"ignoreApproval":false,"id":"X5userfogmn","attributeValues":[]},{"name":"Negative, HIV unknown, Age unknown","created":"2023-08-12T03:42:58.549","lastUpdated":"2023-08-12T03:42:58.549","translations":[],"lastUpdatedBy":{"id":"M5zQapPyTZI","code":"admin","name":"admin admin","displayName":"admin admin","username":"admin"},"categoryCombo":{"id":"epRjlDZBrJL"},"categoryOptions":[{"id":"OGXWo79Rw0G"},{"id":"bpham0JX5kw"},{"id":"AdOGHNfJJgn"}],"ignoreApproval":false,"id":"x1IrlKI6HSn","attributeValues":[]},{"name":"Negative, HIV+, 15-19","created":"2023-08-06T05:32:33.238","lastUpdated":"2023-08-06T05:32:33.238","translations":[],"lastUpdatedBy":{"id":"M5zQapPyTZI","code":"admin","name":"admin admin","displayName":"admin admin","username":"admin"},"categoryCombo":{"id":"epRjlDZBrJL"},"categoryOptions":[{"id":"Vuc1BJSOorP"},{"id":"bpham0JX5kw"},{"id":"JBgOaIyUEJQ"}],"ignoreApproval":false,"id":"WdG6yD0IJXf","attributeValues":[]},{"name":"Negative, HIV+, 20-24","created":"2023-08-06T05:32:33.239","lastUpdated":"2023-08-06T05:32:33.239","translations":[],"lastUpdatedBy":{"id":"M5zQapPyTZI","code":"admin","name":"admin admin","displayName":"admin admin","username":"admin"},"categoryCombo":{"id":"epRjlDZBrJL"},"categoryOptions":[{"id":"bhx5ONCot8V"},{"id":"bpham0JX5kw"},{"id":"JBgOaIyUEJQ"}],"ignoreApproval":false,"id":"E3s1Hggs72m","attributeValues":[]},{"name":"Negative, HIV+, 25-29","created":"2023-08-06T05:32:33.239","lastUpdated":"2023-08-06T05:32:33.239","translations":[],"lastUpdatedBy":{"id":"M5zQapPyTZI","code":"admin","name":"admin admin","displayName":"admin admin","username":"admin"},"categoryCombo":{"id":"epRjlDZBrJL"},"categoryOptions":[{"id":"TM5zVeshQyh"},{"id":"bpham0JX5kw"},{"id":"JBgOaIyUEJQ"}],"ignoreApproval":false,"id":"Kdr1IdiGugu","attributeValues":[]},{"name":"Negative, HIV+, 30-34","created":"2023-08-06T05:32:33.240","lastUpdated":"2023-08-06T05:32:33.240","translations":[],"lastUpdatedBy":{"id":"M5zQapPyTZI","code":"admin","name":"admin admin","displayName":"admin admin","username":"admin"},"categoryCombo":{"id":"epRjlDZBrJL"},"categoryOptions":[{"id":"kKiTqS6Vd0X"},{"id":"bpham0JX5kw"},{"id":"JBgOaIyUEJQ"}],"ignoreApproval":false,"id":"gLJP7MxS9if","attributeValues":[]},{"name":"Negative, HIV+, 35-39","created":"2023-08-06T05:32:33.240","lastUpdated":"2023-08-06T05:32:33.240","translations":[],"lastUpdatedBy":{"id":"M5zQapPyTZI","code":"admin","name":"admin admin","displayName":"admin admin","username":"admin"},"categoryCombo":{"id":"epRjlDZBrJL"},"categoryOptions":[{"id":"bpham0JX5kw"},{"id":"JBgOaIyUEJQ"},{"id":"nqR6XXBM6cn"}],"ignoreApproval":false,"id":"EGXyeMxwAWj","attributeValues":[]},{"name":"Negative, HIV+, 40-44","created":"2023-08-06T05:32:33.241","lastUpdated":"2023-08-06T05:32:33.241","translations":[],"lastUpdatedBy":{"id":"M5zQapPyTZI","code":"admin","name":"admin admin","displayName":"admin admin","username":"admin"},"categoryCombo":{"id":"epRjlDZBrJL"},"categoryOptions":[{"id":"dib8KvXIgHA"},{"id":"bpham0JX5kw"},{"id":"JBgOaIyUEJQ"}],"ignoreApproval":false,"id":"HXOug1hyoNv","attributeValues":[]},{"name":"Negative, HIV+, 45-49","created":"2023-08-06T05:32:33.242","lastUpdated":"2023-08-06T05:32:33.242","translations":[],"lastUpdatedBy":{"id":"M5zQapPyTZI","code":"admin","name":"admin admin","displayName":"admin admin","username":"admin"},"categoryCombo":{"id":"epRjlDZBrJL"},"categoryOptions":[{"id":"DkgPXtR2ZXX"},{"id":"bpham0JX5kw"},{"id":"JBgOaIyUEJQ"}],"ignoreApproval":false,"id":"gRekw3O1xcf","attributeValues":[]},{"name":"Negative, HIV+, 50+","created":"2023-08-06T05:32:33.242","lastUpdated":"2023-08-06T05:32:33.242","translations":[],"lastUpdatedBy":{"id":"M5zQapPyTZI","code":"admin","name":"admin admin","displayName":"admin admin","username":"admin"},"categoryCombo":{"id":"epRjlDZBrJL"},"categoryOptions":[{"id":"lvri1b2Mq4v"},{"id":"bpham0JX5kw"},{"id":"JBgOaIyUEJQ"}],"ignoreApproval":false,"id":"lIsZHbQPbcx","attributeValues":[]},{"name":"Negative, HIV+, Age unknown","created":"2023-08-12T03:42:58.547","lastUpdated":"2023-08-12T03:42:58.547","translations":[],"lastUpdatedBy":{"id":"M5zQapPyTZI","code":"admin","name":"admin admin","displayName":"admin admin","username":"admin"},"categoryCombo":{"id":"epRjlDZBrJL"},"categoryOptions":[{"id":"OGXWo79Rw0G"},{"id":"bpham0JX5kw"},{"id":"JBgOaIyUEJQ"}],"ignoreApproval":false,"id":"NjWFuz6ySYN","attributeValues":[]},{"name":"Negative, HIV-, 15-19","created":"2023-08-06T05:32:33.243","lastUpdated":"2023-08-06T05:32:33.243","translations":[],"lastUpdatedBy":{"id":"M5zQapPyTZI","code":"admin","name":"admin admin","displayName":"admin admin","username":"admin"},"categoryCombo":{"id":"epRjlDZBrJL"},"categoryOptions":[{"id":"Vuc1BJSOorP"},{"id":"HhshCacVCbE"},{"id":"bpham0JX5kw"}],"ignoreApproval":false,"id":"UF3mhxBL8fj","attributeValues":[]},{"name":"Negative, HIV-, 20-24","created":"2023-08-06T05:32:33.243","lastUpdated":"2023-08-06T05:32:33.243","translations":[],"lastUpdatedBy":{"id":"M5zQapPyTZI","code":"admin","name":"admin admin","displayName":"admin admin","username":"admin"},"categoryCombo":{"id":"epRjlDZBrJL"},"categoryOptions":[{"id":"bhx5ONCot8V"},{"id":"HhshCacVCbE"},{"id":"bpham0JX5kw"}],"ignoreApproval":false,"id":"h8PaHZJ7vdr","attributeValues":[]},{"name":"Negative, HIV-, 25-29","created":"2023-08-06T05:32:33.244","lastUpdated":"2023-08-06T05:32:33.244","translations":[],"lastUpdatedBy":{"id":"M5zQapPyTZI","code":"admin","name":"admin admin","displayName":"admin admin","username":"admin"},"categoryCombo":{"id":"epRjlDZBrJL"},"categoryOptions":[{"id":"TM5zVeshQyh"},{"id":"HhshCacVCbE"},{"id":"bpham0JX5kw"}],"ignoreApproval":false,"id":"y7sWSIoE5My","attributeValues":[]},{"name":"Negative, HIV-, 30-34","created":"2023-08-06T05:32:33.245","lastUpdated":"2023-08-06T05:32:33.245","translations":[],"lastUpdatedBy":{"id":"M5zQapPyTZI","code":"admin","name":"admin admin","displayName":"admin admin","username":"admin"},"categoryCombo":{"id":"epRjlDZBrJL"},"categoryOptions":[{"id":"kKiTqS6Vd0X"},{"id":"HhshCacVCbE"},{"id":"bpham0JX5kw"}],"ignoreApproval":false,"id":"WrKr1s7MMy7","attributeValues":[]},{"name":"Negative, HIV-, 35-39","created":"2023-08-06T05:32:33.245","lastUpdated":"2023-08-06T05:32:33.245","translations":[],"lastUpdatedBy":{"id":"M5zQapPyTZI","code":"admin","name":"admin admin","displayName":"admin admin","username":"admin"},"categoryCombo":{"id":"epRjlDZBrJL"},"categoryOptions":[{"id":"HhshCacVCbE"},{"id":"bpham0JX5kw"},{"id":"nqR6XXBM6cn"}],"ignoreApproval":false,"id":"NOmBRdBEXNe","attributeValues":[]},{"name":"Negative, HIV-, 40-44","created":"2023-08-06T05:32:33.246","lastUpdated":"2023-08-06T05:32:33.246","translations":[],"lastUpdatedBy":{"id":"M5zQapPyTZI","code":"admin","name":"admin admin","displayName":"admin admin","username":"admin"},"categoryCombo":{"id":"epRjlDZBrJL"},"categoryOptions":[{"id":"dib8KvXIgHA"},{"id":"HhshCacVCbE"},{"id":"bpham0JX5kw"}],"ignoreApproval":false,"id":"mIXoMldykbE","attributeValues":[]},{"name":"Negative, HIV-, 45-49","created":"2023-08-06T05:32:33.246","lastUpdated":"2023-08-06T05:32:33.246","translations":[],"lastUpdatedBy":{"id":"M5zQapPyTZI","code":"admin","name":"admin admin","displayName":"admin admin","username":"admin"},"categoryCombo":{"id":"epRjlDZBrJL"},"categoryOptions":[{"id":"DkgPXtR2ZXX"},{"id":"HhshCacVCbE"},{"id":"bpham0JX5kw"}],"ignoreApproval":false,"id":"YBIQLb9Kqi9","attributeValues":[]},{"name":"Negative, HIV-, 50+","created":"2023-08-06T05:32:33.247","lastUpdated":"2023-08-06T05:32:33.247","translations":[],"lastUpdatedBy":{"id":"M5zQapPyTZI","code":"admin","name":"admin admin","displayName":"admin admin","username":"admin"},"categoryCombo":{"id":"epRjlDZBrJL"},"categoryOptions":[{"id":"HhshCacVCbE"},{"id":"lvri1b2Mq4v"},{"id":"bpham0JX5kw"}],"ignoreApproval":false,"id":"hB3zjPpwI3x","attributeValues":[]},{"name":"Negative, HIV-, Age unknown","created":"2023-08-12T03:42:58.548","lastUpdated":"2023-08-12T03:42:58.548","translations":[],"lastUpdatedBy":{"id":"M5zQapPyTZI","code":"admin","name":"admin admin","displayName":"admin admin","username":"admin"},"categoryCombo":{"id":"epRjlDZBrJL"},"categoryOptions":[{"id":"OGXWo79Rw0G"},{"id":"HhshCacVCbE"},{"id":"bpham0JX5kw"}],"ignoreApproval":false,"id":"Oebt5q3hR5b","attributeValues":[]},{"name":"Positive, HIV unknown, 15-19","created":"2023-08-06T05:32:33.233","lastUpdated":"2023-08-06T05:32:33.233","translations":[],"lastUpdatedBy":{"id":"M5zQapPyTZI","code":"admin","name":"admin admin","displayName":"admin admin","username":"admin"},"categoryCombo":{"id":"epRjlDZBrJL"},"categoryOptions":[{"id":"Vuc1BJSOorP"},{"id":"AdOGHNfJJgn"},{"id":"AQP88yK3VJk"}],"ignoreApproval":false,"id":"lJki8uLlAm4","attributeValues":[]},{"name":"Positive, HIV unknown, 20-24","created":"2023-08-06T05:32:33.234","lastUpdated":"2023-08-06T05:32:33.234","translations":[],"lastUpdatedBy":{"id":"M5zQapPyTZI","code":"admin","name":"admin admin","displayName":"admin admin","username":"admin"},"categoryCombo":{"id":"epRjlDZBrJL"},"categoryOptions":[{"id":"bhx5ONCot8V"},{"id":"AdOGHNfJJgn"},{"id":"AQP88yK3VJk"}],"ignoreApproval":false,"id":"Opi6zi5byx7","attributeValues":[]},{"name":"Positive, HIV unknown, 25-29","created":"2023-08-06T05:32:33.234","lastUpdated":"2023-08-06T05:32:33.234","translations":[],"lastUpdatedBy":{"id":"M5zQapPyTZI","code":"admin","name":"admin admin","displayName":"admin admin","username":"admin"},"categoryCombo":{"id":"epRjlDZBrJL"},"categoryOptions":[{"id":"TM5zVeshQyh"},{"id":"AdOGHNfJJgn"},{"id":"AQP88yK3VJk"}],"ignoreApproval":false,"id":"iKMs3vHoCML","attributeValues":[]},{"name":"Positive, HIV unknown, 30-34","created":"2023-08-06T05:32:33.235","lastUpdated":"2023-08-06T05:32:33.235","translations":[],"lastUpdatedBy":{"id":"M5zQapPyTZI","code":"admin","name":"admin admin","displayName":"admin admin","username":"admin"},"categoryCombo":{"id":"epRjlDZBrJL"},"categoryOptions":[{"id":"kKiTqS6Vd0X"},{"id":"AdOGHNfJJgn"},{"id":"AQP88yK3VJk"}],"ignoreApproval":false,"id":"bxRWfUGcs2V","attributeValues":[]},{"name":"Positive, HIV unknown, 35-39","created":"2023-08-06T05:32:33.235","lastUpdated":"2023-08-06T05:32:33.235","translations":[],"lastUpdatedBy":{"id":"M5zQapPyTZI","code":"admin","name":"admin admin","displayName":"admin admin","username":"admin"},"categoryCombo":{"id":"epRjlDZBrJL"},"categoryOptions":[{"id":"AdOGHNfJJgn"},{"id":"nqR6XXBM6cn"},{"id":"AQP88yK3VJk"}],"ignoreApproval":false,"id":"Y0Mcslm21k8","attributeValues":[]},{"name":"Positive, HIV unknown, 40-44","created":"2023-08-06T05:32:33.236","lastUpdated":"2023-08-06T05:32:33.236","translations":[],"lastUpdatedBy":{"id":"M5zQapPyTZI","code":"admin","name":"admin admin","displayName":"admin admin","username":"admin"},"categoryCombo":{"id":"epRjlDZBrJL"},"categoryOptions":[{"id":"dib8KvXIgHA"},{"id":"AdOGHNfJJgn"},{"id":"AQP88yK3VJk"}],"ignoreApproval":false,"id":"zv7DiUyANbi","attributeValues":[]},{"name":"Positive, HIV unknown, 45-49","created":"2023-08-06T05:32:33.237","lastUpdated":"2023-08-06T05:32:33.237","translations":[],"lastUpdatedBy":{"id":"M5zQapPyTZI","code":"admin","name":"admin admin","displayName":"admin admin","username":"admin"},"categoryCombo":{"id":"epRjlDZBrJL"},"categoryOptions":[{"id":"DkgPXtR2ZXX"},{"id":"AdOGHNfJJgn"},{"id":"AQP88yK3VJk"}],"ignoreApproval":false,"id":"xdlvXS8IkH8","attributeValues":[]},{"name":"Positive, HIV unknown, 50+","created":"2023-08-06T05:32:33.237","lastUpdated":"2023-08-06T05:32:33.237","translations":[],"lastUpdatedBy":{"id":"M5zQapPyTZI","code":"admin","name":"admin admin","displayName":"admin admin","username":"admin"},"categoryCombo":{"id":"epRjlDZBrJL"},"categoryOptions":[{"id":"lvri1b2Mq4v"},{"id":"AdOGHNfJJgn"},{"id":"AQP88yK3VJk"}],"ignoreApproval":false,"id":"NSlbfIvcDUN","attributeValues":[]},{"name":"Positive, HIV unknown, Age unknown","created":"2023-08-12T03:42:58.546","lastUpdated":"2023-08-12T03:42:58.546","translations":[],"lastUpdatedBy":{"id":"M5zQapPyTZI","code":"admin","name":"admin admin","displayName":"admin admin","username":"admin"},"categoryCombo":{"id":"epRjlDZBrJL"},"categoryOptions":[{"id":"OGXWo79Rw0G"},{"id":"AdOGHNfJJgn"},{"id":"AQP88yK3VJk"}],"ignoreApproval":false,"id":"HUb57ZqPzbp","attributeValues":[]},{"name":"Positive, HIV+, 15-19","created":"2023-08-06T05:32:33.222","lastUpdated":"2023-08-06T05:32:33.222","translations":[],"lastUpdatedBy":{"id":"M5zQapPyTZI","code":"admin","name":"admin admin","displayName":"admin admin","username":"admin"},"categoryCombo":{"id":"epRjlDZBrJL"},"categoryOptions":[{"id":"Vuc1BJSOorP"},{"id":"JBgOaIyUEJQ"},{"id":"AQP88yK3VJk"}],"ignoreApproval":false,"id":"uGV7JujsjpR","attributeValues":[]},{"name":"Positive, HIV+, 20-24","created":"2023-08-06T05:32:33.223","lastUpdated":"2023-08-06T05:32:33.223","translations":[],"lastUpdatedBy":{"id":"M5zQapPyTZI","code":"admin","name":"admin admin","displayName":"admin admin","username":"admin"},"categoryCombo":{"id":"epRjlDZBrJL"},"categoryOptions":[{"id":"bhx5ONCot8V"},{"id":"JBgOaIyUEJQ"},{"id":"AQP88yK3VJk"}],"ignoreApproval":false,"id":"Uhw1VYQ7m68","attributeValues":[]},{"name":"Positive, HIV+, 25-29","created":"2023-08-06T05:32:33.224","lastUpdated":"2023-08-06T05:32:33.224","translations":[],"lastUpdatedBy":{"id":"M5zQapPyTZI","code":"admin","name":"admin admin","displayName":"admin admin","username":"admin"},"categoryCombo":{"id":"epRjlDZBrJL"},"categoryOptions":[{"id":"TM5zVeshQyh"},{"id":"JBgOaIyUEJQ"},{"id":"AQP88yK3VJk"}],"ignoreApproval":false,"id":"kd2WCPkvRHL","attributeValues":[]},{"name":"Positive, HIV+, 30-34","created":"2023-08-06T05:32:33.225","lastUpdated":"2023-08-06T05:32:33.225","translations":[],"lastUpdatedBy":{"id":"M5zQapPyTZI","code":"admin","name":"admin admin","displayName":"admin admin","username":"admin"},"categoryCombo":{"id":"epRjlDZBrJL"},"categoryOptions":[{"id":"kKiTqS6Vd0X"},{"id":"JBgOaIyUEJQ"},{"id":"AQP88yK3VJk"}],"ignoreApproval":false,"id":"aOufRjFMrsK","attributeValues":[]},{"name":"Positive, HIV+, 35-39","created":"2023-08-06T05:32:33.225","lastUpdated":"2023-08-06T05:32:33.225","translations":[],"lastUpdatedBy":{"id":"M5zQapPyTZI","code":"admin","name":"admin admin","displayName":"admin admin","username":"admin"},"categoryCombo":{"id":"epRjlDZBrJL"},"categoryOptions":[{"id":"JBgOaIyUEJQ"},{"id":"nqR6XXBM6cn"},{"id":"AQP88yK3VJk"}],"ignoreApproval":false,"id":"GJTqYQ6Jr0B","attributeValues":[]},{"name":"Positive, HIV+, 40-44","created":"2023-08-06T05:32:33.226","lastUpdated":"2023-08-06T05:32:33.226","translations":[],"lastUpdatedBy":{"id":"M5zQapPyTZI","code":"admin","name":"admin admin","displayName":"admin admin","username":"admin"},"categoryCombo":{"id":"epRjlDZBrJL"},"categoryOptions":[{"id":"dib8KvXIgHA"},{"id":"JBgOaIyUEJQ"},{"id":"AQP88yK3VJk"}],"ignoreApproval":false,"id":"RATIWlf7E4I","attributeValues":[]},{"name":"Positive, HIV+, 45-49","created":"2023-08-06T05:32:33.227","lastUpdated":"2023-08-06T05:32:33.227","translations":[],"lastUpdatedBy":{"id":"M5zQapPyTZI","code":"admin","name":"admin admin","displayName":"admin admin","username":"admin"},"categoryCombo":{"id":"epRjlDZBrJL"},"categoryOptions":[{"id":"DkgPXtR2ZXX"},{"id":"JBgOaIyUEJQ"},{"id":"AQP88yK3VJk"}],"ignoreApproval":false,"id":"GsmxrqLI1X8","attributeValues":[]},{"name":"Positive, HIV+, 50+","created":"2023-08-06T05:32:33.227","lastUpdated":"2023-08-06T05:32:33.227","translations":[],"lastUpdatedBy":{"id":"M5zQapPyTZI","code":"admin","name":"admin admin","displayName":"admin admin","username":"admin"},"categoryCombo":{"id":"epRjlDZBrJL"},"categoryOptions":[{"id":"lvri1b2Mq4v"},{"id":"JBgOaIyUEJQ"},{"id":"AQP88yK3VJk"}],"ignoreApproval":false,"id":"bt5xg3XYwL6","attributeValues":[]},{"name":"Positive, HIV+, Age unknown","created":"2023-08-12T03:42:58.541","lastUpdated":"2023-08-12T03:42:58.541","translations":[],"lastUpdatedBy":{"id":"M5zQapPyTZI","code":"admin","name":"admin admin","displayName":"admin admin","username":"admin"},"categoryCombo":{"id":"epRjlDZBrJL"},"categoryOptions":[{"id":"OGXWo79Rw0G"},{"id":"JBgOaIyUEJQ"},{"id":"AQP88yK3VJk"}],"ignoreApproval":false,"id":"xO5PHYPyYDR","attributeValues":[]},{"name":"Positive, HIV-, 15-19","created":"2023-08-06T05:32:33.228","lastUpdated":"2023-08-06T05:32:33.228","translations":[],"lastUpdatedBy":{"id":"M5zQapPyTZI","code":"admin","name":"admin admin","displayName":"admin admin","username":"admin"},"categoryCombo":{"id":"epRjlDZBrJL"},"categoryOptions":[{"id":"Vuc1BJSOorP"},{"id":"HhshCacVCbE"},{"id":"AQP88yK3VJk"}],"ignoreApproval":false,"id":"ioBh4QJoP7x","attributeValues":[]},{"name":"Positive, HIV-, 20-24","created":"2023-08-06T05:32:33.229","lastUpdated":"2023-08-06T05:32:33.229","translations":[],"lastUpdatedBy":{"id":"M5zQapPyTZI","code":"admin","name":"admin admin","displayName":"admin admin","username":"admin"},"categoryCombo":{"id":"epRjlDZBrJL"},"categoryOptions":[{"id":"bhx5ONCot8V"},{"id":"HhshCacVCbE"},{"id":"AQP88yK3VJk"}],"ignoreApproval":false,"id":"HAxSMzDrYRh","attributeValues":[]},{"name":"Positive, HIV-, 25-29","created":"2023-08-06T05:32:33.229","lastUpdated":"2023-08-06T05:32:33.229","translations":[],"lastUpdatedBy":{"id":"M5zQapPyTZI","code":"admin","name":"admin admin","displayName":"admin admin","username":"admin"},"categoryCombo":{"id":"epRjlDZBrJL"},"categoryOptions":[{"id":"TM5zVeshQyh"},{"id":"HhshCacVCbE"},{"id":"AQP88yK3VJk"}],"ignoreApproval":false,"id":"dMZufwDcZlT","attributeValues":[]},{"name":"Positive, HIV-, 30-34","created":"2023-08-06T05:32:33.230","lastUpdated":"2023-08-06T05:32:33.230","translations":[],"lastUpdatedBy":{"id":"M5zQapPyTZI","code":"admin","name":"admin admin","displayName":"admin admin","username":"admin"},"categoryCombo":{"id":"epRjlDZBrJL"},"categoryOptions":[{"id":"kKiTqS6Vd0X"},{"id":"HhshCacVCbE"},{"id":"AQP88yK3VJk"}],"ignoreApproval":false,"id":"MJTJOIEgN1C","attributeValues":[]},{"name":"Positive, HIV-, 35-39","created":"2023-08-06T05:32:33.230","lastUpdated":"2023-08-06T05:32:33.230","translations":[],"lastUpdatedBy":{"id":"M5zQapPyTZI","code":"admin","name":"admin admin","displayName":"admin admin","username":"admin"},"categoryCombo":{"id":"epRjlDZBrJL"},"categoryOptions":[{"id":"HhshCacVCbE"},{"id":"nqR6XXBM6cn"},{"id":"AQP88yK3VJk"}],"ignoreApproval":false,"id":"Xe0adcFisPw","attributeValues":[]},{"name":"Positive, HIV-, 40-44","created":"2023-08-06T05:32:33.231","lastUpdated":"2023-08-06T05:32:33.231","translations":[],"lastUpdatedBy":{"id":"M5zQapPyTZI","code":"admin","name":"admin admin","displayName":"admin admin","username":"admin"},"categoryCombo":{"id":"epRjlDZBrJL"},"categoryOptions":[{"id":"dib8KvXIgHA"},{"id":"HhshCacVCbE"},{"id":"AQP88yK3VJk"}],"ignoreApproval":false,"id":"sydHPdc4tHT","attributeValues":[]},{"name":"Positive, HIV-, 45-49","created":"2023-08-06T05:32:33.232","lastUpdated":"2023-08-06T05:32:33.232","translations":[],"lastUpdatedBy":{"id":"M5zQapPyTZI","code":"admin","name":"admin admin","displayName":"admin admin","username":"admin"},"categoryCombo":{"id":"epRjlDZBrJL"},"categoryOptions":[{"id":"DkgPXtR2ZXX"},{"id":"HhshCacVCbE"},{"id":"AQP88yK3VJk"}],"ignoreApproval":false,"id":"OcJ7IoC4iAJ","attributeValues":[]},{"name":"Positive, HIV-, 50+","created":"2023-08-06T05:32:33.232","lastUpdated":"2023-08-06T05:32:33.232","translations":[],"lastUpdatedBy":{"id":"M5zQapPyTZI","code":"admin","name":"admin admin","displayName":"admin admin","username":"admin"},"categoryCombo":{"id":"epRjlDZBrJL"},"categoryOptions":[{"id":"HhshCacVCbE"},{"id":"lvri1b2Mq4v"},{"id":"AQP88yK3VJk"}],"ignoreApproval":false,"id":"jgHPeZLSTKr","attributeValues":[]},{"name":"Positive, HIV-, Age unknown","created":"2023-08-12T03:42:58.545","lastUpdated":"2023-08-12T03:42:58.545","translations":[],"lastUpdatedBy":{"id":"M5zQapPyTZI","code":"admin","name":"admin admin","displayName":"admin admin","username":"admin"},"categoryCombo":{"id":"epRjlDZBrJL"},"categoryOptions":[{"id":"OGXWo79Rw0G"},{"id":"HhshCacVCbE"},{"id":"AQP88yK3VJk"}],"ignoreApproval":false,"id":"i47ecjnwgFV","attributeValues":[]},{"code":"default","name":"default","created":"2023-06-12T09:48:07.914","lastUpdated":"2023-06-12T09:48:07.916","translations":[],"categoryCombo":{"id":"bjDvmb4bfuf"},"categoryOptions":[{"id":"xYerKDKCefk"}],"ignoreApproval":false,"id":"HllvX50cXC0","attributeValues":[]}]}